pflacco/__init__.py
pflacco/classical_ela_features.py
pflacco/local_optima_network_features.py
pflacco/misc_features.py
pflacco/sampling.py
pflacco/utils.py
tests/__init__.py
tests/classical_ela_features_test.py
tests/conftest.py
tests/generate_resources.py
tests/local_optima_network_features_test.py
tests/misc_features_test.py
tests/sampling_test.py
pflacco-1.2.2.dist-info/LICENSE
pflacco-1.2.2.dist-info/METADATA
pflacco-1.2.2.dist-info/WHEEL
pflacco-1.2.2.dist-info/top_level.txt
pflacco-1.2.2.dist-info/RECORD
