Metadata-Version: 2.1
Name: pflacco
Version: 1.2.2
Summary: A Python implementation and extension to the R package flacco for computing ELA features.
Home-page: https://pypi.org/project/pflacco/
Author: Raphael Patrick Prager
Author-email: raphael.prager@gmx.de
License: MIT
Classifier: Programming Language :: Python :: 3
Classifier: License :: OSI Approved :: MIT License
Classifier: Operating System :: OS Independent
License-File: LICENSE
Requires-Dist: numpy ~=1.24.3
Requires-Dist: scikit-learn ~=1.2.2
Requires-Dist: pyDOE ~=0.3.8
Requires-Dist: scipy ~=1.10.1
Requires-Dist: pandas <2.1.0,>=1.2.1
Requires-Dist: numdifftools ~=0.9.40
Requires-Dist: SALib ~=1.4.5
